kitsune/__init__.py
kitsune/amp/__init__.py
kitsune/amp/autocast.py
kitsune/amp/config.py
kitsune/amp/optimizer.py
kitsune/amp/scaler.py
kitsune/api/__init__.py
kitsune/api/device_config.py
kitsune/api/optimizer.py
kitsune/api/optimizer_new.py
kitsune/api/optimizer_v2.py
kitsune/api/simple_optimizer.py
kitsune/backends/__init__.py
kitsune/backends/apple_optimizer.py
kitsune/backends/backend_selector.py
kitsune/backends/experimental.py
kitsune/backends/rtx_optimizer.py
kitsune/backends/stable.py
kitsune/backends/t4_optimizer.py
kitsune/core/__init__.py
kitsune/core/compiler.py
kitsune/core/executor.py
kitsune/core/graph.py
kitsune/core/optimized_wrapper.py
kitsune/core/scheduler.py
kitsune/core/task.py
kitsune/cuda/__init__.py
kitsune/cuda/events.py
kitsune/cuda/graph_capture.py
kitsune/cuda/graphs.py
kitsune/cuda/stream_pool.py
kitsune/fallback/__init__.py
kitsune/fusion/__init__.py
kitsune/fusion/detector.py
kitsune/fusion/engine.py
kitsune/fusion/patterns.py
kitsune/memory/__init__.py
kitsune/memory/double_buffer.py
kitsune/memory/lifetime.py
kitsune/memory/pool.py
kitsune/memory/prefetch.py
kitsune/profiler/__init__.py
kitsune/profiler/cuda_timer.py
kitsune/profiler/memory_tracker.py
kitsune/profiler/metrics.py
kitsune/profiler/reporter.py
kitsune/pytorch/__init__.py
kitsune/pytorch/graph_capture.py
kitsune/utils/__init__.py
kitsune/utils/logging.py
torch_kitsune-0.3.0.dist-info/licenses/LICENSE
torch_kitsune-0.3.0.dist-info/METADATA
torch_kitsune-0.3.0.dist-info/WHEEL
torch_kitsune-0.3.0.dist-info/top_level.txt
torch_kitsune-0.3.0.dist-info/RECORD
