Metadata-Version: 2.4
Name: torch-kitsune
Version: 0.3.0
Summary: High-performance PyTorch optimization framework: 4x speedup on T4, 45x on Apple Silicon via hardware-specific backends, JIT compilation, and intelligent memory management
Author-email: Jeeth Kataria <jeethkataria9798@icloud.com>
Maintainer-email: Jeeth Kataria <jeethkataria9798@icloud.com>
License: MIT
Project-URL: Homepage, https://github.com/jeeth-kataria/Kitsune_optimization
Project-URL: Documentation, https://jeeth-kataria.github.io/Kitsune_optimization
Project-URL: Repository, https://github.com/jeeth-kataria/Kitsune_optimization
Project-URL: Changelog, https://github.com/jeeth-kataria/Kitsune_optimization/blob/main/CHANGELOG.md
Project-URL: Bug Tracker, https://github.com/jeeth-kataria/Kitsune_optimization/issues
Project-URL: Release Notes, https://github.com/jeeth-kataria/Kitsune_optimization/releases
Keywords: pytorch,cuda,optimization,inference,gpu,deep-learning,apple-silicon,mps,t4,rtx,jit,torch-compile,fp16,mixed-precision,memory-pooling,performance
Classifier: Development Status :: 4 - Beta
Classifier: Intended Audience :: Developers
Classifier: Intended Audience :: Science/Research
Classifier: License :: OSI Approved :: MIT License
Classifier: Programming Language :: Python :: 3
Classifier: Programming Language :: Python :: 3.10
Classifier: Programming Language :: Python :: 3.11
Classifier: Programming Language :: Python :: 3.12
Classifier: Topic :: Scientific/Engineering :: Artificial Intelligence
Classifier: Topic :: Software Development :: Libraries :: Python Modules
Classifier: Topic :: System :: Distributed Computing
Classifier: Environment :: GPU :: NVIDIA CUDA
Classifier: Environment :: MacOS X
Classifier: Operating System :: OS Independent
Requires-Python: >=3.10
License-File: LICENSE
Requires-Dist: torch>=2.0.0
Requires-Dist: numpy>=1.21.0
Provides-Extra: triton
Requires-Dist: triton>=2.1.0; sys_platform == "linux" and extra == "triton"
Provides-Extra: dev
Requires-Dist: pytest>=7.0.0; extra == "dev"
Requires-Dist: pytest-benchmark>=4.0.0; extra == "dev"
Requires-Dist: black>=23.0.0; extra == "dev"
Requires-Dist: isort>=5.12.0; extra == "dev"
Requires-Dist: mypy>=1.0.0; extra == "dev"
Requires-Dist: ruff>=0.1.0; extra == "dev"
Requires-Dist: build>=1.0.0; extra == "dev"
Requires-Dist: twine>=4.0.0; extra == "dev"
Provides-Extra: viz
Requires-Dist: matplotlib>=3.5.0; extra == "viz"
Requires-Dist: tensorboard>=2.10.0; extra == "viz"
Provides-Extra: docs
Requires-Dist: mkdocs>=1.5.0; extra == "docs"
Requires-Dist: mkdocs-material>=9.4.0; extra == "docs"
Requires-Dist: mkdocstrings[python]>=0.24.0; extra == "docs"
Requires-Dist: mkdocs-git-revision-date-localized-plugin>=1.2.0; extra == "docs"
Provides-Extra: all
Requires-Dist: torch-kitsune[dev,docs,triton,viz]; extra == "all"
Dynamic: license-file
